pycnpj_cpf/__init__.py
pycnpj_cpf/__main__.py
pycnpj_cpf/cli.py
pycnpj_cpf/core.py
pycnpj_cpf-0.2.2.dist-info/METADATA
pycnpj_cpf-0.2.2.dist-info/WHEEL
pycnpj_cpf-0.2.2.dist-info/entry_points.txt
pycnpj_cpf-0.2.2.dist-info/licenses/LICENSE
pycnpj_cpf-0.2.2.dist-info/RECORD
