Metadata-Version: 2.4
Name: pycnpj-cpf
Version: 0.2.2
Summary: CNPJ and CPF validator
Project-URL: repository, https://github.com/carlos-moreno/pycnpj-cpf
Author-email: Carlos Moreno <omorenodovale@gmail.com>
License:                     GNU GENERAL PUBLIC LICENSE
License-File: LICENSE
Requires-Python: >=3.8
Requires-Dist: click
Requires-Dist: rich
Requires-Dist: rich-click
